{
  "pateo": {
    "Entradas": [
      { "name": "Gambas do Algarve", "price": "26.50€", "description": "Grelhadas com sal marinho e limão." },
      { "name": "Ameijoas à Bulhão Pato", "price": "24.00€", "description": "Com coentros, alho e azeite de primeira extração." }
    ],
    "Pratos Principais": [
      { "name": "Lombo de Bacalhau Confitado", "price": "34.50€", "description": "Com grão-de-bico, couve e emulsão de alho." },
      { "name": "Arroz de Marisco do Bairro", "price": "42.00€", "description": "Arroz caldoso com o melhor que o mar oferece hoje." }
    ],
    "Sobremesas": [
      { "name": "Avelã ao Cubo", "price": "12.50€", "description": "Texturas de avelã e chocolate amargo." }
    ]
  },
  "taberna": {
    "Petiscos": [
      { "name": "Pipocas de Coirato", "price": "6.00€", "description": "Croquantes e viciantes com especiarias." },
      { "name": "Peixinhos da Horta", "price": "9.50€", "description": "Feijão verde em polme crocante com tártaro de algas." },
      { "name": "Croquetes de Novilho", "price": "8.00€", "description": "Com mostarda caseira e picles." }
    ],
    "Pratos": [
      { "name": "Bifana de Atum", "price": "16.00€", "description": "No pão de bolo do caco com emulsão de coentros." }
    ]
  },
  "pizzaria": {
    "Pizzas": [
      { "name": "Margherita de Lisboa", "price": "15.50€", "description": "Tomate, mozzarella fior di latte e manjericão fresco." },
      { "name": "Diavola", "price": "18.00€", "description": "Salame picante de Spianata Calabra e chili." }
    ]
  },
  "popup": {
    "Sugestões": [
      { "name": "Menu Degustação Noélia", "price": "65.00€", "description": "Uma viagem pelos sabores do Algarve com o toque da Chef Noélia." }
    ]
  }
}
